[
  {
    "key": "dpr",
    "value": "1.25",
    "domain": "facebook.com",
    "path": "/",
    "hostOnly": false,
    "creation": "2026-05-03T04:10:50.375Z",
    "lastAccessed": "2026-05-03T04:10:55.306Z",
    "secure": false,
    "httpOnly": false,
    "expires": "2027-05-03T04:10:54.000Z"
  },
  {
    "key": "datr",
    "value": "JxUwaU3_UooimS0RHQo7vAXH",
    "domain": "facebook.com",
    "path": "/",
    "hostOnly": false,
    "creation": "2026-05-03T04:10:50.385Z",
    "lastAccessed": "2026-05-03T04:10:55.306Z",
    "secure": false,
    "httpOnly": false,
    "expires": "2027-05-03T04:10:54.000Z"
  },
  {
    "key": "sb",
    "value": "LhUwaRk-Afp9D3hwA5vUUbPs",
    "domain": "facebook.com",
    "path": "/",
    "hostOnly": false,
    "creation": "2026-05-03T04:10:50.386Z",
    "lastAccessed": "2026-05-03T04:10:55.306Z",
    "secure": false,
    "httpOnly": false,
    "expires": "2027-05-03T04:10:54.000Z"
  },
  {
    "key": "ps_l",
    "value": "1",
    "domain": "facebook.com",
    "path": "/",
    "hostOnly": false,
    "creation": "2026-05-03T04:10:50.386Z",
    "lastAccessed": "2026-05-03T04:10:55.306Z",
    "secure": false,
    "httpOnly": false,
    "expires": "2027-05-03T04:10:54.000Z"
  },
  {
    "key": "ps_n",
    "value": "1",
    "domain": "facebook.com",
    "path": "/",
    "hostOnly": false,
    "creation": "2026-05-03T04:10:50.386Z",
    "lastAccessed": "2026-05-03T04:10:55.306Z",
    "secure": false,
    "httpOnly": false,
    "expires": "2027-05-03T04:10:54.000Z"
  },
  {
    "key": "ar_debug",
    "value": "1",
    "domain": "facebook.com",
    "path": "/",
    "hostOnly": false,
    "creation": "2026-05-03T04:10:50.389Z",
    "lastAccessed": "2026-05-03T04:10:55.306Z",
    "secure": false,
    "httpOnly": false,
    "expires": "2027-05-03T04:10:54.000Z"
  },
  {
    "key": "wd",
    "value": "936x731",
    "domain": "facebook.com",
    "path": "/",
    "hostOnly": false,
    "creation": "2026-05-03T04:10:50.389Z",
    "lastAccessed": "2026-05-03T04:10:55.306Z",
    "secure": false,
    "httpOnly": false,
    "expires": "2027-05-03T04:10:54.000Z"
  },
  {
    "key": "fr",
    "value": "1gtXcx7OIDYlbtvh4.AWfX6DZRlutMiaH2FqxyF1TxWw5uKsjPVxhHRymIEthoCE_SI1s.BpNu4N..AAA.0.0.Bp9srO.AWfmIyJ7JleUHRFefjcvaPXsxAo",
    "domain": "facebook.com",
    "path": "/",
    "hostOnly": false,
    "creation": "2026-05-03T04:10:50.797Z",
    "lastAccessed": "2026-05-03T04:10:55.306Z",
    "secure": true,
    "httpOnly": true,
    "expires": "2026-08-01T04:10:54.000Z"
  }
]